AlgoAnalyzer/Analyzer.py
AlgoAnalyzer/__init__.py
AlgoAnalyzer/chart/__init__.py
AlgoAnalyzer/chart/chart.py
AlgoAnalyzer/technicals/__init__.py
AlgoAnalyzer/technicals/ema_crossover.py
AlgoAnalyzer/technicals/macd.py
AlgoAnalyzer/technicals/sma_crossover.py
AlgoAnalyzer-0.0.6.dist-info/LICENSE
AlgoAnalyzer-0.0.6.dist-info/METADATA
AlgoAnalyzer-0.0.6.dist-info/WHEEL
AlgoAnalyzer-0.0.6.dist-info/top_level.txt
AlgoAnalyzer-0.0.6.dist-info/RECORD
