Metadata-Version: 2.1
Name: AlgoAnalyzer
Version: 0.0.6
Summary: AlgoAnalyzer is a package for designing your trading strategies and run simulations to backtest your strategies and check their robustness
Home-page: https://github.com/Jash271/AlgoAnalyzer
Author: Jash Shah
Author-email: shahjash271@gmail.com
License: MIT
Platform: UNKNOWN
Classifier: Development Status :: 4 - Beta
Classifier: License :: OSI Approved :: MIT License
Classifier: Programming Language :: Python
Classifier: Topic :: Software Development :: Libraries
Classifier: Topic :: Software Development :: Libraries :: Python Modules
Classifier: Intended Audience :: Developers
Requires-Python: >=3.6
License-File: LICENSE
Requires-Dist: yfinance
Requires-Dist: plotly
